README
setup.cfg
setup.py
customnoseplugins/__init__.py
customnoseplugins/fileoutput.py
customnoseplugins/planloader.py
customnoseplugins/tools.py
customnoseplugins.egg-info/PKG-INFO
customnoseplugins.egg-info/SOURCES.txt
customnoseplugins.egg-info/dependency_links.txt
customnoseplugins.egg-info/entry_points.txt
customnoseplugins.egg-info/top_level.txt