Metadata-Version: 1.0
Name: customnoseplugins
Version: 4.0.2
Summary: test plan plugins for the nose testing framework
Home-page: UNKNOWN
Author: bao hongbin
Author-email: hongbin.bao@gmail.com
License: MIT
Platform: UNKNOWN
